frosty_ai/__init__.py
frosty_ai/frosty.py
frosty_ai-1.6.dist-info/METADATA
frosty_ai-1.6.dist-info/WHEEL
frosty_ai-1.6.dist-info/top_level.txt
frosty_ai-1.6.dist-info/RECORD
