Metadata-Version: 2.4
Name: frosty_ai
Version: 1.6
Summary: A Python package for seamless multi-LLM routing, observability, and LLM-agnostic integration.
Home-page: https://docs.gofrosty.ai/frosty-ai-docs/frosty-ai-documentation
Author: FrostyAI
Author-email: brittany@gofrosty.ai
Classifier: Programming Language :: Python :: 3
Classifier: License :: OSI Approved :: MIT License
Classifier: Operating System :: OS Independent
Requires-Python: >=3.7
Requires-Dist: requests
Requires-Dist: openai>=0.28.0
Requires-Dist: mistralai>=1.5.0
Requires-Dist: anthropic>=0.49.0
Requires-Dist: urllib3<1.27,>=1.25.4
Dynamic: author
Dynamic: author-email
Dynamic: classifier
Dynamic: description
Dynamic: description-content-type
Dynamic: home-page
Dynamic: requires-dist
Dynamic: requires-python
Dynamic: summary
